environ/__init__.py
environ/compat.py
environ/environ.py
environ/fileaware_mapping.py
fdemmer_django_environ-0.11.3.dist-info/AUTHORS.rst
fdemmer_django_environ-0.11.3.dist-info/LICENSE.txt
fdemmer_django_environ-0.11.3.dist-info/METADATA
fdemmer_django_environ-0.11.3.dist-info/WHEEL
fdemmer_django_environ-0.11.3.dist-info/top_level.txt
fdemmer_django_environ-0.11.3.dist-info/RECORD
