Metadata-Version: 2.1
Name: fdemmer-django-environ
Version: 0.11.3
Summary: A package that allows you to utilize 12factor inspired environment variables to configure your Django application.
Home-page: https://django-environ.readthedocs.org
Author: Daniele Faraglia
Author-email: daniele.faraglia@gmail.com
Maintainer: Serghei Iakovlev
Maintainer-email: egrep@protonmail.ch
License: MIT
Project-URL: Documentation, https://django-environ.readthedocs.org
Project-URL: Funding, https://opencollective.com/django-environ
Project-URL: Say Thanks!, https://saythanks.io/to/joke2k
Project-URL: Changelog, https://django-environ.readthedocs.org/en/latest/changelog.html
Project-URL: Bug Tracker, https://github.com/joke2k/django-environ/issues
Project-URL: Source Code, https://github.com/joke2k/django-environ
Keywords: environment,django,variables,12factor
Platform: any
Classifier: Development Status :: 5 - Production/Stable
Classifier: Framework :: Django
Classifier: Framework :: Django :: 1.11
Classifier: Framework :: Django :: 2.0
Classifier: Framework :: Django :: 2.1
Classifier: Framework :: Django :: 2.2
Classifier: Framework :: Django :: 3.0
Classifier: Framework :: Django :: 3.1
Classifier: Framework :: Django :: 3.2
Classifier: Framework :: Django :: 4.0
Classifier: Framework :: Django :: 4.1
Classifier: Framework :: Django :: 4.2
Classifier: Framework :: Django :: 5.0
Classifier: Operating System :: OS Independent
Classifier: Intended Audience :: Developers
Classifier: Natural Language :: English
Classifier: Programming Language :: Python
Classifier: Programming Language :: Python :: 3
Classifier: Programming Language :: Python :: 3.6
Classifier: Programming Language :: Python :: 3.7
Classifier: Programming Language :: Python :: 3.8
Classifier: Programming Language :: Python :: 3.9
Classifier: Programming Language :: Python :: 3.10
Classifier: Programming Language :: Python :: 3.11
Classifier: Programming Language :: Python :: 3.12
Classifier: Programming Language :: Python :: Implementation :: CPython
Classifier: Programming Language :: Python :: Implementation :: PyPy
Classifier: Topic :: Software Development :: Libraries :: Python Modules
Classifier: Topic :: Utilities
Classifier: License :: OSI Approved :: MIT License
Requires-Python: >=3.6,<4
License-File: LICENSE.txt
License-File: AUTHORS.rst
Provides-Extra: develop
Requires-Dist: coverage[toml] >=5.0a4 ; extra == 'develop'
Requires-Dist: pytest >=4.6.11 ; extra == 'develop'
Requires-Dist: furo ==2021.8.*,>=2021.8.17b43 ; extra == 'develop'
Requires-Dist: sphinx >=3.5.0 ; extra == 'develop'
Requires-Dist: sphinx-notfound-page ; extra == 'develop'
Provides-Extra: docs
Requires-Dist: furo ==2021.8.*,>=2021.8.17b43 ; extra == 'docs'
Requires-Dist: sphinx >=3.5.0 ; extra == 'docs'
Requires-Dist: sphinx-notfound-page ; extra == 'docs'
Provides-Extra: testing
Requires-Dist: coverage[toml] >=5.0a4 ; extra == 'testing'
Requires-Dist: pytest >=4.6.11 ; extra == 'testing'
